dskernels/__init__.py
dskernels/libblockedflash.so
dskernels/libdeepspeedft.so
dskernels/version.py
deepspeed_kernels-0.0.1.dev1698255861.dist-info/LICENSE
deepspeed_kernels-0.0.1.dev1698255861.dist-info/METADATA
deepspeed_kernels-0.0.1.dev1698255861.dist-info/WHEEL
deepspeed_kernels-0.0.1.dev1698255861.dist-info/top_level.txt
deepspeed_kernels-0.0.1.dev1698255861.dist-info/RECORD
